[{"varName":"Andrés","varFirstSurname":"Salazar","varSecondSurname":"Vargas","varId":"104561234","varGroup":"","varSiglasCourses":""},{"varName":"Laura","varFirstSurname":"Méndez","varSecondSurname":"Chacón","varId":"209345678","varGroup":"","varSiglasCourses":""},{"varName":"María Fernanda","varFirstSurname":"Zúñiga","varSecondSurname":"Soto","varId":"308237766","varGroup":"","varSiglasCourses":""},{"varName":"Carlos","varFirstSurname":"Esquivel","varSecondSurname":"Rodríguez","varId":"103992345","varGroup":"","varSiglasCourses":""},{"varName":"Diana","varFirstSurname":"González","varSecondSurname":"Mora","varId":"408883456","varGroup":"","varSiglasCourses":""},{"varName":"juan","varFirstSurname":"bb","varSecondSurname":"vv","varId":"123","varGroup":"","varSiglasCourses":""}]